MANIFEST.in
setup.py
cve_search/__init__.py
cve_search.egg-info/PKG-INFO
cve_search.egg-info/SOURCES.txt
cve_search.egg-info/dependency_links.txt
cve_search.egg-info/requires.txt
cve_search.egg-info/top_level.txt
cve_search/bin/cve_doc.py
cve_search/bin/cve_refs.py
cve_search/bin/db_dump.py
cve_search/bin/dump_last.py
cve_search/bin/search.py
cve_search/bin/search_cpe.py
cve_search/bin/search_fulltext.py
cve_search/bin/search_irc.py
cve_search/bin/search_xmpp.py
cve_search/doc/html/Installation.html
cve_search/doc/html/Structure.html
cve_search/doc/html/Webcomponent.html
cve_search/doc/html/css/style.css
cve_search/doc/markdown/api.md
cve_search/doc/markdown/installation.md
cve_search/doc/markdown/structure.md
cve_search/doc/markdown/webcomponent.md
cve_search/etc/auth.txt.sample
cve_search/etc/configuration.ini.sample
cve_search/etc/plugins.txt.sample
cve_search/etc/sources.ini.sample
cve_search/lib/Authentication.py
cve_search/lib/CVEs.py
cve_search/lib/Config.py
cve_search/lib/DatabaseLayer.py
cve_search/lib/PluginManager.py
cve_search/lib/Plugins.py
cve_search/lib/ProgressBar.py
cve_search/lib/Query.py
cve_search/lib/Singleton.py
cve_search/lib/Toolkit.py
cve_search/lib/User.py
cve_search/lib/__init__.py
cve_search/lib/cpelist.py
cve_search/lib/authenticationMethods/readme.md
cve_search/sbin/db_blacklist.py
cve_search/sbin/db_cpe_browser.py
cve_search/sbin/db_fulltext.py
cve_search/sbin/db_mgmt.py
cve_search/sbin/db_mgmt_admin.py
cve_search/sbin/db_mgmt_capec.py
cve_search/sbin/db_mgmt_cpe_dictionary.py
cve_search/sbin/db_mgmt_cpe_other_dictionary.py
cve_search/sbin/db_mgmt_create_index.py
cve_search/sbin/db_mgmt_cwe.py
cve_search/sbin/db_mgmt_ref.py
cve_search/sbin/db_notification.py
cve_search/sbin/db_ranking.py
cve_search/sbin/db_updater.py
cve_search/sbin/db_whitelist.py
cve_search/test/test.py
cve_search/web/advanced_api.py
cve_search/web/api.py
cve_search/web/index.py
cve_search/web/minimal.py
cve_search/web/static/css/bootstrap.min.css
cve_search/web/static/css/sidebar.css
cve_search/web/static/css/style.css
cve_search/web/static/css/custom/admin.css
cve_search/web/static/css/custom/cve.css
