Metadata-Version: 1.0
Name: cve-search
Version: 1.0.7
Summary: Useful towel-related stuff.
Home-page: http://pypi.python.org/pypi/cve-search/
Author: cve_search
Author-email: cve-search@cve-search.com
License: UNKNOWN
Platform: UNKNOWN
